localsearchsolverpy/__init__.py
localsearchsolverpy/commons.py
localsearchsolverpy/iterated_local_search.py
localsearchsolverpy/restarting_local_search.py
localsearchsolverpy-0.0.3.dist-info/LICENSE
localsearchsolverpy-0.0.3.dist-info/METADATA
localsearchsolverpy-0.0.3.dist-info/WHEEL
localsearchsolverpy-0.0.3.dist-info/top_level.txt
localsearchsolverpy-0.0.3.dist-info/RECORD
