Metadata-Version: 2.1
Name: localsearchsolverpy
Version: 0.0.3
Summary: A solver based on Local Search
Home-page: https://github.com/fontanf/localsearchsolverpy
Author: Florian Fontan
Author-email: dev@florian-fontan.fr
License: UNKNOWN
Project-URL: Bug Tracker, https://github.com/fontanf/localsearchsolverpy/issues
Platform: UNKNOWN
Classifier: Programming Language :: Python :: 3
Classifier: License :: OSI Approved :: MIT License
Classifier: Operating System :: OS Independent
Requires-Python: >=3.6
License-File: LICENSE
